{"content":"# 高级技巧\n\n## 元素的显示与隐藏\n\n### display 显示\n\n```css\n/* 隐藏对象 */\ndisplay: none\n```\n\n- 特点： 隐藏之后，不再保留位置。\n\n> 配合后面js做特效，比如下拉菜单，原先没有，鼠标经过，显示下拉菜单， 应用极为广泛\n\n### visibility 可见性\n\n```css\n/* 对象可视 */\nvisibility：visible ; 　\n/* 对象隐藏 */\nvisibility：hidden;\n```\n\n- 特点： 隐藏之后，继续保留原有位置。\n\n### overflow 溢出\n\n- 检索或设置当对象的内容超过其指定高度及宽度时如何管理内容\n\n属性值         | 描述\n----------- | ---------------------\n**visible** | 不剪切内容也不添加滚动条\n**hidden**  | 不显示超过对象尺寸的内容，超出的部分隐藏掉\n**scroll**  | 不管超出内容否，总是显示滚动条\n**auto**    | 超出自动显示滚动条，不超出不显示滚动条\n\n应用：\n\n1. 清除浮动\n2. 隐藏超出内容，隐藏掉, 不允许内容超过父盒子。\n\n### 总结\n\n属性             | 区别          | 用途\n-------------- | ----------- | -----------------------------------------\n**display**    | 隐藏对象，不保留位置  | 配合后面js做特效，比如下拉菜单，原先没有，鼠标经过，显示下拉菜单， 应用极为广泛\n**visibility** | 隐藏对象，保留位置   | 使用较少\n**overflow**   | 只是隐藏超出大小的部分 | 1\\. 可以清除浮动 2\\. 保证盒子里面的内容不会超出该盒子范围\n\n##  CSS用户界面样式\n\n###  鼠标样式cursor\n\n设置或检索在对象上移动的鼠标指针采用何种系统预定义的光标形状\n\n```css\na:hover {\n    cursor: value;\n}\n```\n\n | 属性值          | 描述       |\n| --------------- | ---------- |\n| **default**     | 小白  默认 |\n| **pointer**     | 小手       |\n| **move**        | 移动       |\n| **text**        | 文本       |\n| **not-allowed** | 禁止       |\n\n### 轮廓线 outline\n\n```css\noutline : outline-color ||outline-style || outline-width \n```\n\n```css\noutline : outline-color ||outline-style || outline-width \n```\n\n一般都直接去掉:\n\n```css\noutline: 0;\noutline: none;\n```\n\n### 防止拖拽文本域resize\n\n```html\n<textarea  style=\"resize: none;\"></textarea>\n```\n\n## vertical-align 垂直对齐\n\n```css\nvertical-align : baseline |top |middle |bottom \n```\n\nvertical-align 不影响块级元素中的内容对齐，它只针对于**行内元素**或者**行内块元素**\n\n行内块元素， **通常用来控制图片/表单与文字的对齐**\n\n### 图片、表单和文字对齐\n\n![1498467742995](/assets/1498467742995.png)\n\n### 去除图片底侧空白缝隙\n\n图片或者表单等行内块元素，他的底线会和父级盒子的基线对齐\n\n- 给img vertical-align:middle | top| bottom等等。  让图片不要和基线对齐\n- 给img 添加 display：block; 转换为块级元素就不会存在问题了\n\n## 溢出的文字省略号显示\n\n```css\n/*1. 先强制一行内显示文本*/\n    white-space: nowrap;\n/*2. 超出的部分隐藏*/\n    overflow: hidden;\n/*3. 文字用省略号替代超出的部分*/\n    text-overflow: ellipsis;\n```\n\n## CSS精灵技术（sprite) \n\nCSS 精灵其实是将网页中的一些背景图像整合到一张大图中（精灵图）\n\n## 滑动门\n\n![](https://upload-images.jianshu.io/upload_images/2710245-eee233e8ae11c271.png?imageMogr2/auto-orient/strip|imageView2/2/w/259/format/webp)\n\n## 扩展\n\n### margin负值\n\n- 负边距+定位：水平垂直居中\n- 压住盒子相邻边框\n  - 需要添加浮动 \n\n### CSS三角\n\n- 将盒子宽高设置为0，然后设置四个边框\n\n```css\ndiv {\n            width: 0;\n            height: 0;\n            border-style: solid;\n            border-width: 20px;\n            border-color: pink skyblue deepskyblue darkcyan;\n}\n```\n","commitList":[{"date":"2021-10-08T12:45:10+08:00","author":"cjiping","message":"doc开发期 构建期调整","hash":"704efe7455b7fb2fbd81ec60099191ff982e639a"},{"date":"2021-10-07T19:38:58+08:00","author":"My","message":"init","hash":"4e0456332231ba0523aa526415f9982377358870"}],"hasMoreCommit":false,"totalCommits":0}