{"content":"# 虚拟化的必要条件\n\n- 安全性\n- 保真性\n- 高效性\n\n# 第一类和第二类虚拟机管理程序\n\n![enter image description here](https://yinyuhang.github.io/img/cloudcomputing/Hypervisor.png)\n\n- **客户操作系统**\n- **宿主操作系统**\n\n# 高效虚拟化技术\n\n## 在不支持虚拟化的平台上实现虚拟化\n\n_系统切换_\n\n## 虚拟化的开销\n\n# 虚拟机管理程序是正确的微内核吗\n\n# 内存虚拟化\n\n- 嵌套页表的硬件扩展\n- 回收内存\n\n# IO虚拟化\n\n- IO MMU\n- 设备域\n- 单根IO虚拟化\n\n# 虚拟装置\n\n# 多核CPU上的虚拟机\n\n**去重**\n\n# 授权问题\n\n# 云\n- 按需自助服务\n- 普适的网络访问\n- 资源池\n- 快速可伸缩\n- 服务可计量\n  \n## 云即服务\n\n## 虚拟机迁移\n\n## 检查点\n\n\n","commitList":[{"date":"2021-10-08T12:45:10+08:00","author":"cjiping","message":"doc开发期 构建期调整","hash":"704efe7455b7fb2fbd81ec60099191ff982e639a"},{"date":"2021-10-07T19:38:58+08:00","author":"My","message":"init","hash":"4e0456332231ba0523aa526415f9982377358870"}],"hasMoreCommit":false,"totalCommits":0}